[
{"user_id": 0, "sw_name": "crowdsignals.algosnap.com", "sw_version": "1.0(1)", "device_id": "352622063881655", "device_type": "smartphone", "timezone": -8, "type": "gsm", "start": 1454961196000000000, "end": 1454961197000000000, "mcc": ["310"], "mnc": ["410"], "lac": [37127], "cid": [107884559], "timestamps": [1454961196003000000]},
{"user_id": 0, "sw_name": "crowdsignals.algosnap.com", "sw_version": "1.0(1)", "device_id": "352622063881655", "device_type": "smartphone", "timezone": -8, "type": "gsm", "start": 1454961207000000000, "end": 1454961208000000000, "mcc": ["310"], "mnc": ["410"], "lac": [37127], "cid": [108762376], "timestamps": [1454961207005000000]},
{"user_id": 0, "sw_name": "crowdsignals.algosnap.com", "sw_version": "1.0(1)", "device_id": "352622063881655", "device_type": "smartphone", "timezone": -8, "type": "gsm", "start": 1454961218000000000, "end": 1454961219000000000, "mcc": ["310"], "mnc": ["410"], "lac": [37127], "cid": [108762376], "timestamps": [1454961218027000000]},
{"user_id": 0, "sw_name": "crowdsignals.algosnap.com", "sw_version": "1.0(1)", "device_id": "352622063881655", "device_type": "smartphone", "timezone": -8, "type": "gsm", "start": 1454961229000000000, "end": 1454961230000000000, "mcc": ["310"], "mnc": ["410"], "lac": [37127], "cid": [108762376], "timestamps": [1454961229009000000]},
{"user_id": 0, "sw_name": "crowdsignals.algosnap.com", "sw_version": "1.0(1)", "device_id": "352622063881655", "device_type": "smartphone", "timezone": -8, "type": "gsm", "start": 1454961240000000000, "end": 1454961241000000000, "mcc": ["310"], "mnc": ["410"], "lac": [37127], "cid": [108762376], "timestamps": [1454961240005000000]},
{"user_id": 0, "sw_name": "crowdsignals.algosnap.com", "sw_version": "1.0(1)", "device_id": "352622063881655", "device_type": "smartphone", "timezone": -8, "type": "gsm", "start": 1454961251000000000, "end": 1454961252000000000, "mcc": ["310"], "mnc": ["410"], "lac": [37127], "cid": [108762376], "timestamps": [1454961251019000000]},
{"user_id": 0, "sw_name": "crowdsignals.algosnap.com", "sw_version": "1.0(1)", "device_id": "352622063881655", "device_type": "smartphone", "timezone": -8, "type": "gsm", "start": 1454961262000000000, "end": 1454961263000000000, "mcc": ["310"], "mnc": ["410"], "lac": [37127], "cid": [108762376], "timestamps": [1454961262032000000]},
{"user_id": 0, "sw_name": "crowdsignals.algosnap.com", "sw_version": "1.0(1)", "device_id": "352622063881655", "device_type": "smartphone", "timezone": -8, "type": "gsm", "start": 1454961273000000000, "end": 1454961274000000000, "mcc": ["310"], "mnc": ["410"], "lac": [37127], "cid": [108762376], "timestamps": [1454961273015000000]},
{"user_id": 0, "sw_name": "crowdsignals.algosnap.com", "sw_version": "1.0(1)", "device_id": "352622063881655", "device_type": "smartphone", "timezone": -8, "type": "gsm", "start": 1454961284000000000, "end": 1454961285000000000, "mcc": ["310"], "mnc": ["410"], "lac": [37127], "cid": [108762376], "timestamps": [1454961284014000000]},
{"user_id": 0, "sw_name": "crowdsignals.algosnap.com", "sw_version": "1.0(1)", "device_id": "352622063881655", "device_type": "smartphone", "timezone": -8, "type": "gsm", "start": 1454961295000000000, "end": 1454961296000000000, "mcc": ["310"], "mnc": ["410"], "lac": [37127], "cid": [108762376], "timestamps": [1454961295030000000]},
{"user_id": 0, "sw_name": "crowdsignals.algosnap.com", "sw_version": "1.0(1)", "device_id": "352622063881655", "device_type": "smartphone", "timezone": -8, "type": "gsm", "start": 1454961306000000000, "end": 1454961307000000000, "mcc": ["310"], "mnc": ["410"], "lac": [37127], "cid": [108762376], "timestamps": [1454961306010000000]}
]