[
{"user_id": 0, "sw_name": "crowdsignals.algosnap.com", "sw_version": "1.0(1)", "device_id": "352622063881655", "device_type": "smartphone", "timezone": -8, "type": "phonestate", "start": 1454961973335000000, "end": 1454961973335000000, "event_type": ["DataActivity"], "data": ["DATA_ACTIVITY_OUT"], "number": ["null"], "timestamps": [1454961973335000000]},
{"user_id": 0, "sw_name": "crowdsignals.algosnap.com", "sw_version": "1.0(1)", "device_id": "352622063881655", "device_type": "smartphone", "timezone": -8, "type": "phonestate", "start": 1454961974341000000, "end": 1454961974341000000, "event_type": ["DataActivity"], "data": ["DATA_ACTIVITY_IN"], "number": ["null"], "timestamps": [1454961974341000000]},
{"user_id": 0, "sw_name": "crowdsignals.algosnap.com", "sw_version": "1.0(1)", "device_id": "352622063881655", "device_type": "smartphone", "timezone": -8, "type": "phonestate", "start": 1454961975353000000, "end": 1454961975353000000, "event_type": ["DataActivity"], "data": ["DATA_ACTIVITY_NONE"], "number": ["null"], "timestamps": [1454961975353000000]},
{"user_id": 0, "sw_name": "crowdsignals.algosnap.com", "sw_version": "1.0(1)", "device_id": "352622063881655", "device_type": "smartphone", "timezone": -8, "type": "phonestate", "start": 1454962057285000000, "end": 1454962057285000000, "event_type": ["DataActivity"], "data": ["DATA_ACTIVITY_INOUT"], "number": ["null"], "timestamps": [1454962057285000000]},
{"user_id": 0, "sw_name": "crowdsignals.algosnap.com", "sw_version": "1.0(1)", "device_id": "352622063881655", "device_type": "smartphone", "timezone": -8, "type": "phonestate", "start": 1454962058289000000, "end": 1454962058289000000, "event_type": ["DataActivity"], "data": ["DATA_ACTIVITY_NONE"], "number": ["null"], "timestamps": [1454962058289000000]}
]